pymupdf4llm_enhanced_mcp/main.py
pymupdf4llm_enhanced_mcp-0.1.2.dist-info/METADATA
pymupdf4llm_enhanced_mcp-0.1.2.dist-info/WHEEL
pymupdf4llm_enhanced_mcp-0.1.2.dist-info/entry_points.txt
pymupdf4llm_enhanced_mcp-0.1.2.dist-info/licenses/LICENSE
pymupdf4llm_enhanced_mcp-0.1.2.dist-info/RECORD
