Metadata-Version: 2.4
Name: pymupdf4llm-enhanced-mcp
Version: 0.1.2
Summary: 基于 PyMuPDF4LLM 和 Tiktoken 的 PDF 解析与分块 MCP 服务器
License-File: LICENSE
Requires-Python: >=3.13
Requires-Dist: pymupdf4llm>=0.0.27
Requires-Dist: tiktoken>=0.12.0
